puppetboard/__init__.py
puppetboard/app.py
puppetboard/core.py
puppetboard/default_settings.py
puppetboard/docker_settings.py
puppetboard/errors.py
puppetboard/forms.py
puppetboard/utils.py
puppetboard/version.py
puppetboard/static/favicon.ico
puppetboard/static/favicon.svg
puppetboard/static/css/fonts.css
puppetboard/static/css/puppetboard.css
puppetboard/static/css/radiator.css
puppetboard/static/custom-natural-time-delta/natural-time-delta.js
puppetboard/static/fonts/cousine/d6lIkaiiRdih4SpP_SAvzAbt.woff2
puppetboard/static/fonts/cousine/d6lIkaiiRdih4SpP_SQvzA.woff2
puppetboard/static/fonts/cousine/d6lIkaiiRdih4SpP_SYvzAbt.woff2
puppetboard/static/fonts/cousine/d6lIkaiiRdih4SpP_ScvzAbt.woff2
puppetboard/static/fonts/cousine/d6lIkaiiRdih4SpP_SgvzAbt.woff2
puppetboard/static/fonts/cousine/d6lIkaiiRdih4SpP_SkvzAbt.woff2
puppetboard/static/fonts/cousine/d6lIkaiiRdih4SpP_SovzAbt.woff2
puppetboard/static/fonts/cousine/d6lIkaiiRdih4SpP_SsvzAbt.woff2
puppetboard/static/fonts/lato/S6u8w4BMUTPHjxsAUi-qJCY.woff2
puppetboard/static/fonts/lato/S6u8w4BMUTPHjxsAXC-q.woff2
puppetboard/static/fonts/lato/S6u9w4BMUTPHh6UVSwaPGR_p.woff2
puppetboard/static/fonts/lato/S6u9w4BMUTPHh6UVSwiPGQ.woff2
puppetboard/static/fonts/lato/S6u_w4BMUTPHjxsI5wq_FQft1dw.woff2
puppetboard/static/fonts/lato/S6u_w4BMUTPHjxsI5wq_Gwft.woff2
puppetboard/static/fonts/lato/S6uyw4BMUTPHjx4wXg.woff2
puppetboard/static/fonts/lato/S6uyw4BMUTPHjxAwXjeu.woff2
puppetboard/static/fonts/open-sans/memSYaGs126MiZpBA-UvWbX2vVnXBbObj2OVZyOOSr4dVJWUgsjZ0B4gaVI.woff2
puppetboard/static/fonts/open-sans/memSYaGs126MiZpBA-UvWbX2vVnXBbObj2OVZyOOSr4dVJWUgsjZ0B4iaVIGxA.woff2
puppetboard/static/fonts/open-sans/memSYaGs126MiZpBA-UvWbX2vVnXBbObj2OVZyOOSr4dVJWUgsjZ0B4jaVIGxA.woff2
puppetboard/static/fonts/open-sans/memSYaGs126MiZpBA-UvWbX2vVnXBbObj2OVZyOOSr4dVJWUgsjZ0B4kaVIGxA.woff2
puppetboard/static/fonts/open-sans/memSYaGs126MiZpBA-UvWbX2vVnXBbObj2OVZyOOSr4dVJWUgsjZ0B4saVIGxA.woff2
puppetboard-5.4.0.dist-info/LICENSE
puppetboard-5.4.0.dist-info/METADATA
puppetboard-5.4.0.dist-info/WHEEL
puppetboard-5.4.0.dist-info/top_level.txt
puppetboard-5.4.0.dist-info/RECORD
