Metadata-Version: 2.1
Name: puppetboard
Version: 5.4.0
Summary: Web frontend for PuppetDB
Home-page: https://github.com/voxpupuli/puppetboard
Author: Vox Pupuli
Author-email: voxpupuli@groups.io
License: Apache License 2.0
Keywords: puppet puppetdb puppetboard
Classifier: Development Status :: 5 - Production/Stable
Classifier: Environment :: Web Environment
Classifier: Framework :: Flask
Classifier: Intended Audience :: System Administrators
Classifier: Natural Language :: English
Classifier: License :: OSI Approved :: Apache Software License
Classifier: Operating System :: POSIX
Classifier: Programming Language :: Python :: 3
Classifier: Programming Language :: Python :: 3.8
Classifier: Programming Language :: Python :: 3.9
Classifier: Programming Language :: Python :: 3.10
Classifier: Programming Language :: Python :: 3.11
Requires-Python: >=3.8.0
License-File: LICENSE
Requires-Dist: certifi ==2024.2.2
Requires-Dist: charset-normalizer ==3.3.2
Requires-Dist: click ==8.1.7
Requires-Dist: commonmark ==0.9.1
Requires-Dist: Flask ==3.0.2
Requires-Dist: Flask-APScheduler ==1.13.1
Requires-Dist: Flask-Caching ==2.1.0
Requires-Dist: Flask-WTF ==1.2.1
Requires-Dist: idna ==3.6
Requires-Dist: itsdangerous ==2.1.2
Requires-Dist: Jinja2 ==3.1.3
Requires-Dist: MarkupSafe ==2.1.5
Requires-Dist: packaging ==23.2
Requires-Dist: pyparsing ==3.1.1
Requires-Dist: pypuppetdb ==3.2.0
Requires-Dist: requests ==2.31.0
Requires-Dist: typing-extensions ==4.10.0
Requires-Dist: urllib3 ==2.2.1
Requires-Dist: Werkzeug ==3.0.1
Requires-Dist: WTForms ==3.1.2
Requires-Dist: zipp ==3.17.0
Provides-Extra: test
Requires-Dist: pep8 ==1.7.1 ; extra == 'test'
Requires-Dist: coverage ==7.4.3 ; extra == 'test'
Requires-Dist: mock ==5.1.0 ; extra == 'test'
Requires-Dist: pytest ==8.0.2 ; extra == 'test'
Requires-Dist: pylint ==3.1.0 ; extra == 'test'
Requires-Dist: pytest-pylint ==0.21.0 ; extra == 'test'
Requires-Dist: pytest-cov ==4.1.0 ; extra == 'test'
Requires-Dist: pytest-mock ==3.12.0 ; extra == 'test'
Requires-Dist: pytest-mypy ==0.10.3 ; extra == 'test'
Requires-Dist: pytest-randomly ==3.15.0 ; extra == 'test'
Requires-Dist: cov-core ==1.15.0 ; extra == 'test'
Requires-Dist: beautifulsoup4 ==4.12.3 ; extra == 'test'
Requires-Dist: bandit ==1.7.7 ; extra == 'test'
Requires-Dist: mypy ==1.8.0 ; extra == 'test'
Requires-Dist: types-requests ==2.31.0.20240218 ; extra == 'test'
Requires-Dist: types-setuptools ==69.1.0.20240301 ; extra == 'test'
Requires-Dist: types-toml ==0.10.8.7 ; extra == 'test'
